uefi_r2/__init__.py
uefi_r2/__init__.pyi
uefi_r2/py.typed
uefi_r2/test_internal.py
uefi_r2/uefi_analyzer.py
uefi_r2/uefi_analyzer.pyi
uefi_r2/uefi_protocols.py
uefi_r2/uefi_protocols.pyi
uefi_r2/uefi_scanner.py
uefi_r2/uefi_scanner.pyi
uefi_r2/uefi_smm.py
uefi_r2/uefi_tables.py
uefi_r2/uefi_tables.pyi
uefi_r2/uefi_te.py
uefi_r2/uefi_te.pyi
uefi_r2/uefi_types.py
uefi_r2/uefi_utils.py
uefi_r2-1.2.4.dist-info/LICENSE
uefi_r2-1.2.4.dist-info/METADATA
uefi_r2-1.2.4.dist-info/WHEEL
uefi_r2-1.2.4.dist-info/top_level.txt
uefi_r2-1.2.4.dist-info/RECORD
