Metadata-Version: 2.1
Name: uefi-r2
Version: 1.2.4
Summary: Tools for analyzing UEFI firmware using radare2/rizin
Home-page: https://github.com/binarly-io/uefi_r2
Author: FwHunt team
Author-email: fwhunt@binarly.io
License: GPL-3.0
Platform: Platform Independent
Classifier: Development Status :: 3 - Alpha
Classifier: License :: OSI Approved :: GNU General Public License v3 (GPLv3)
Classifier: Operating System :: OS Independent
Classifier: Programming Language :: Python :: 3
Requires-Dist: click (>=7)
Requires-Dist: rzpipe (==0.1.2)
Requires-Dist: pyyaml (~=5.4.1)
Requires-Dist: shared-memory38 ; python_version >= "3.6" and python_version < "3.8"
